CHANGELOG.txt
LICENSE.txt
MANIFEST.in
README.md
setup.py
rathureqpy/__init__.py
rathureqpy/list_utils.py
rathureqpy/logic_utils.py
rathureqpy/math_language.py
rathureqpy/math_utils.py
rathureqpy/matrix.py
rathureqpy.egg-info/PKG-INFO
rathureqpy.egg-info/SOURCES.txt
rathureqpy.egg-info/dependency_links.txt
rathureqpy.egg-info/top_level.txt