Metadata-Version: 2.2
Name: rathureqpy
Version: 0.2.0
Summary: Manipulating lists, basic mathematical functions and LaTeX-like writing
Home-page: 
Author: Arthur Quersin
Author-email: arthur.quersin@gmail.com
License: MIT
Keywords: lists,math,matrix
Classifier: Development Status :: 5 - Production/Stable
Classifier: Intended Audience :: Education
Classifier: Operating System :: Microsoft :: Windows :: Windows 10
Classifier: License :: OSI Approved :: MIT License
Classifier: Programming Language :: Python :: 3
License-File: LICENSE.txt
Dynamic: author
Dynamic: author-email
Dynamic: classifier
Dynamic: description
Dynamic: description-content-type
Dynamic: keywords
Dynamic: license
Dynamic: summary
